pyIFD/ADQ1.py
pyIFD/ADQ2.py
pyIFD/ADQ3.py
pyIFD/AlphaHat.npy
pyIFD/BLK.py
pyIFD/CAGI.py
pyIFD/CFA1.py
pyIFD/CFA2.py
pyIFD/DCT.py
pyIFD/ELA.py
pyIFD/GHOST.py
pyIFD/MMasks.npy
pyIFD/NADQ.py
pyIFD/NOI1.py
pyIFD/NOI2.py
pyIFD/NOI4.py
pyIFD/NOI5.py
pyIFD/PMasks.npy
pyIFD/SupportVector.npy
pyIFD/__init__.py
pyIFD/util.py
pyIFD/__pycache__/NOI2.cpython-39.pyc
pyIFD-0.0.3.dist-info/LICENSE
pyIFD-0.0.3.dist-info/METADATA
pyIFD-0.0.3.dist-info/WHEEL
pyIFD-0.0.3.dist-info/top_level.txt
pyIFD-0.0.3.dist-info/RECORD
